{
  "main": {
    "id": "a1268d99bb64bb46",
    "type": "split",
    "children": [
      {
        "id": "521d479ff94f10be",
        "type": "tabs",
        "children": [
          {
            "id": "47ec339c4d0a1031",
            "type": "leaf",
            "state": {
              "type": "empty",
              "state": {}
            }
          }
        ]
      }
    ],
    "direction": "vertical"
  },
  "left": {
    "id": "4ca92571f8bdab4d",
    "type": "split",
    "children": [
      {
        "id": "9105c9dc06ed941a",
        "type": "tabs",
        "children": [
          {
            "id": "275efffabab7cb2e",
            "type": "leaf",
            "state": {
              "type": "file-explorer",
              "state": {
                "sortOrder": "alphabetical"
              }
            }
          },
          {
            "id": "f91de91b9f8465be",
            "type": "leaf",
            "state": {
              "type": "search",
              "state": {
                "query": "",
                "matchingCase": false,
                "explainSearch": false,
                "collapseAll": false,
                "extraContext": false,
                "sortOrder": "alphabetical"
              }
            }
          },
          {
            "id": "c6881ced3ed6524b",
            "type": "leaf",
            "state": {
              "type": "starred",
              "state": {}
            }
          }
        ],
        "currentTab": 1
      }
    ],
    "direction": "horizontal",
    "width": 300
  },
  "right": {
    "id": "3ce81565bdeeeca7",
    "type": "split",
    "children": [
      {
        "id": "40e438f24cf82020",
        "type": "tabs",
        "children": [
          {
            "id": "c07a7a7d7b3a6ad3",
            "type": "leaf",
            "state": {
              "type": "backlink",
              "state": {
                "collapseAll": false,
                "extraContext": false,
                "sortOrder": "alphabetical",
                "showSearch": false,
                "searchQuery": "",
                "backlinkCollapsed": false,
                "unlinkedCollapsed": true
              }
            }
          },
          {
            "id": "86326c27d8429d9d",
            "type": "leaf",
            "state": {
              "type": "outgoing-link",
              "state": {
                "linksCollapsed": false,
                "unlinkedCollapsed": true
              }
            }
          },
          {
            "id": "4e7a10cedcbc8207",
            "type": "leaf",
            "state": {
              "type": "tag",
              "state": {
                "sortOrder": "frequency",
                "useHierarchy": true
              }
            }
          },
          {
            "id": "7fae11bbe7475e47",
            "type": "leaf",
            "state": {
              "type": "outline",
              "state": {}
            }
          }
        ]
      }
    ],
    "direction": "horizontal",
    "width": 300,
    "collapsed": true
  },
  "left-ribbon": {
    "hiddenItems": {
      "switcher:Open quick switcher": false,
      "graph:Open graph view": false,
      "canvas:Create new canvas": false,
      "daily-notes:Open today's daily note": false,
      "templates:Insert template": false,
      "command-palette:Open command palette": false
    }
  },
  "active": "f91de91b9f8465be",
  "lastOpenFiles": []
}